{
  "id": "3146902",
  "name": "tuli",
  "font_family": "iconfont",
  "css_prefix_text": "icon-",
  "description": "",
  "glyphs": [
    {
      "icon_id": "6010800",
      "name": "新",
      "font_class": "xin",
      "unicode": "e945",
      "unicode_decimal": 59717
    },
    {
      "icon_id": "2863",
      "name": "优质",
      "font_class": "youzhi",
      "unicode": "e604",
      "unicode_decimal": 58884
    },
    {
      "icon_id": "1159915",
      "name": "优质",
      "font_class": "youzhi1",
      "unicode": "e633",
      "unicode_decimal": 58931
    },
    {
      "icon_id": "3267417",
      "name": "优质",
      "font_class": "youzhi2",
      "unicode": "e61b",
      "unicode_decimal": 58907
    },
    {
      "icon_id": "6684369",
      "name": "纸飞机",
      "font_class": "zhifeiji",
      "unicode": "e681",
      "unicode_decimal": 59009
    },
    {
      "icon_id": "7568873",
      "name": "24gf-paperPlane",
      "font_class": "24gf-paperPlane",
      "unicode": "e967",
      "unicode_decimal": 59751
    },
    {
      "icon_id": "15560028",
      "name": "优势_优质",
      "font_class": "youshi_youzhi",
      "unicode": "e69c",
      "unicode_decimal": 59036
    },
    {
      "icon_id": "9009443",
      "name": "NEW",
      "font_class": "NEW-copy",
      "unicode": "e889",
      "unicode_decimal": 59529
    },
    {
      "icon_id": "201559",
      "name": "火热",
      "font_class": "huore",
      "unicode": "e602",
      "unicode_decimal": 58882
    },
    {
      "icon_id": "1718318",
      "name": "分享",
      "font_class": "fenxiang1",
      "unicode": "e603",
      "unicode_decimal": 58883
    },
    {
      "icon_id": "6561003",
      "name": "最新更新",
      "font_class": "zuixingengxin",
      "unicode": "e61e",
      "unicode_decimal": 58910
    },
    {
      "icon_id": "201560",
      "name": "喇叭",
      "font_class": "laba",
      "unicode": "e601",
      "unicode_decimal": 58881
    },
    {
      "icon_id": "6337455",
      "name": "点赞",
      "font_class": "dianzan",
      "unicode": "ec7f",
      "unicode_decimal": 60543
    },
    {
      "icon_id": "18171142",
      "name": "回复,转发",
      "font_class": "undo",
      "unicode": "ea17",
      "unicode_decimal": 59927
    },
    {
      "icon_id": "11372777",
      "name": "收藏",
      "font_class": "shoucang1",
      "unicode": "e8c6",
      "unicode_decimal": 59590
    },
    {
      "icon_id": "68268",
      "name": "分享",
      "font_class": "fenxiang",
      "unicode": "e600",
      "unicode_decimal": 58880
    },
    {
      "icon_id": "577341",
      "name": "购物车",
      "font_class": "gouwuche",
      "unicode": "e73d",
      "unicode_decimal": 59197
    },
    {
      "icon_id": "1220301",
      "name": "快递",
      "font_class": "kuaidi",
      "unicode": "e608",
      "unicode_decimal": 58888
    },
    {
      "icon_id": "1249081",
      "name": "支付",
      "font_class": "zhifu",
      "unicode": "e615",
      "unicode_decimal": 58901
    },
    {
      "icon_id": "2076258",
      "name": "客服",
      "font_class": "kefu",
      "unicode": "e88f",
      "unicode_decimal": 59535
    },
    {
      "icon_id": "2076282",
      "name": " 订单",
      "font_class": "dingdan",
      "unicode": "e897",
      "unicode_decimal": 59543
    },
    {
      "icon_id": "3769199",
      "name": "支付",
      "font_class": "zhifu1",
      "unicode": "e8f9",
      "unicode_decimal": 59641
    },
    {
      "icon_id": "9369731",
      "name": "钱包",
      "font_class": "qianbao",
      "unicode": "e60b",
      "unicode_decimal": 58891
    },
    {
      "icon_id": "11372701",
      "name": "收藏",
      "font_class": "shoucang",
      "unicode": "e8b9",
      "unicode_decimal": 59577
    }
  ]
}
